{"_ts":[1569890335],"_r":{"breakdown":{"html":{"bytes":[277192],"requests":[18]},"js":{"bytes":[913681],"requests":[23]},"css":{"bytes":[205761],"requests":[3]},"image":{"bytes":[815573],"requests":[59]},"flash":{"bytes":[0],"requests":[0]},"font":{"bytes":[365752],"requests":[5]},"video":{"bytes":[0],"requests":[0]},"other":{"bytes":[38182],"requests":[6]}},"date":[1569890335],"domElements":[null],"domInteractive":[null],"firstPaint":[null],"fullyLoaded":[null],"id":["191001_7K_1da7cb8cce46db98b789d9a138607fd2"],"loadTime":[null],"render":[null],"SpeedIndex":[null],"TTFB":[null],"videoFrames":[[{"_i":"ms_000000.jpg","_t":0,"_vc":0},{"_i":"ms_019900.jpg","_t":19900,"_vc":100}]],"visualComplete":[null],"lighthouse":[null],"pagespeed":[62]}}