{"_ts":[1541043013],"_r":{"breakdown":{"html":{"bytes":[33328],"requests":[13]},"js":{"bytes":[769581],"requests":[26]},"css":{"bytes":[134434],"requests":[3]},"image":{"bytes":[1990823],"requests":[169]},"flash":{"bytes":[0],"requests":[0]},"font":{"bytes":[125845],"requests":[5]},"video":{"bytes":[0],"requests":[0]},"other":{"bytes":[26853],"requests":[7]}},"date":[1541043013],"domElements":[3786],"domInteractive":[2812],"firstPaint":[2524.6999999999],"fullyLoaded":[10207],"id":["181101_DY_e03ba7a21a4861b45655869afe8eef32"],"loadTime":[6826],"render":[3900],"SpeedIndex":[6191],"TTFB":[1270],"videoFrames":[[{"_i":"ms_000000.jpg","_t":0,"_vc":0},{"_i":"ms_003900.jpg","_t":3900,"_vc":41},{"_i":"ms_004000.jpg","_t":4000,"_vc":69},{"_i":"ms_004100.jpg","_t":4100,"_vc":69},{"_i":"ms_004200.jpg","_t":4200,"_vc":69},{"_i":"ms_004300.jpg","_t":4300,"_vc":69},{"_i":"ms_004500.jpg","_t":4500,"_vc":68},{"_i":"ms_004600.jpg","_t":4600,"_vc":69},{"_i":"ms_005000.jpg","_t":5000,"_vc":69},{"_i":"ms_005100.jpg","_t":5100,"_vc":69},{"_i":"ms_005200.jpg","_t":5200,"_vc":69},{"_i":"ms_005300.jpg","_t":5300,"_vc":69},{"_i":"ms_005400.jpg","_t":5400,"_vc":69},{"_i":"ms_005500.jpg","_t":5500,"_vc":69},{"_i":"ms_005800.jpg","_t":5800,"_vc":69},{"_i":"ms_006000.jpg","_t":6000,"_vc":69},{"_i":"ms_006100.jpg","_t":6100,"_vc":69},{"_i":"ms_006200.jpg","_t":6200,"_vc":69},{"_i":"ms_006600.jpg","_t":6600,"_vc":69},{"_i":"ms_006800.jpg","_t":6800,"_vc":69},{"_i":"ms_007100.jpg","_t":7100,"_vc":67},{"_i":"ms_007400.jpg","_t":7400,"_vc":67},{"_i":"ms_007500.jpg","_t":7500,"_vc":67},{"_i":"ms_007600.jpg","_t":7600,"_vc":67},{"_i":"ms_008200.jpg","_t":8200,"_vc":75},{"_i":"ms_008300.jpg","_t":8300,"_vc":75},{"_i":"ms_008400.jpg","_t":8400,"_vc":76},{"_i":"ms_008500.jpg","_t":8500,"_vc":78},{"_i":"ms_008600.jpg","_t":8600,"_vc":78},{"_i":"ms_008700.jpg","_t":8700,"_vc":78},{"_i":"ms_008900.jpg","_t":8900,"_vc":78},{"_i":"ms_012000.jpg","_t":12000,"_vc":78},{"_i":"ms_012100.jpg","_t":12100,"_vc":80},{"_i":"ms_012200.jpg","_t":12200,"_vc":86},{"_i":"ms_012300.jpg","_t":12300,"_vc":93},{"_i":"ms_012400.jpg","_t":12400,"_vc":100}]],"visualComplete":[12400],"lighthouse":[27],"pagespeed":[57]}}